flask_conditional.py
setup.py
test_conditional.py
flask_conditional.egg-info/PKG-INFO
flask_conditional.egg-info/SOURCES.txt
flask_conditional.egg-info/dependency_links.txt
flask_conditional.egg-info/not-zip-safe
flask_conditional.egg-info/requires.txt
flask_conditional.egg-info/top_level.txt