Metadata-Version: 1.1
Name: flask-conditional
Version: 0.1
Summary: Conditional decorators for Flask routes
Home-page: http://github.com/alfg/flask-conditional
Author: Alfred Gutierrez
Author-email: alf.g.jr@gmail.com
License: MIT
Platform: any
Classifier: Environment :: Web Environment
Classifier: Intended Audience :: Developers
Classifier: License :: OSI Approved :: MIT License
Classifier: Operating System :: OS Independent
Classifier: Programming Language :: Python
Classifier: Topic :: Internet :: WWW/HTTP :: Dynamic Content
Classifier: Topic :: Software Development :: Libraries :: Python Modules
